{
  "_meta": {
    "asset": "product_master",
    "status": "seed",
    "note": "Small real-shaped starter set. Full production set is 244 verified beverage/product entries, each checked against the maker's official spec. Match on FULL product identity, never a brand-name substring (龍 ⊂ 黒龍).",
    "full_size": 244
  },
  "entries": [
    {
      "id": "pm_kokuryu_junmai_ginjo",
      "name_ja": "黒龍 純米吟醸",
      "name_en": "Kokuryu Junmai Ginjo",
      "maker_ja": "黒龍酒造",
      "maker_en": "Kokuryu Sake Brewing Co.",
      "category": "sake",
      "subcategory": "junmai_ginjo",
      "region": "Fukui",
      "abv": 15.5,
      "allergens": [],
      "restrictions": ["contains-alcohol", "no-alcohol:fail"],
      "verified_against": "brewery official spec",
      "verification_rank": "S"
    },
    {
      "id": "pm_dassai_45",
      "name_ja": "獺祭 純米大吟醸 45",
      "name_en": "Dassai Junmai Daiginjo 45",
      "maker_ja": "旭酒造",
      "maker_en": "Asahi Shuzo",
      "category": "sake",
      "subcategory": "junmai_daiginjo",
      "region": "Yamaguchi",
      "abv": 16.0,
      "allergens": [],
      "restrictions": ["contains-alcohol", "no-alcohol:fail"],
      "verified_against": "brewery official spec",
      "verification_rank": "S"
    }
  ]
}
